kego/__init__.py
kego/checks.py
kego/columns.py
kego/constants.py
kego/dataframes.py
kego/debug.py
kego/imports.py
kego/lists.py
kego/logger.py
kego/math.py
kego/normalize.py
kego/parallelize.py
kego/split.py
kego/strings.py
kego/train.py
kego/arc/__init__.py
kego/arc/images.py
kego/ariel/__init__.py
kego/ariel/features.py
kego/ariel/metrics.py
kego/files/__init__.py
kego/files/files.py
kego/files/json.py
kego/metrics/convert.py
kego/metrics/eefs_concordance_index.py
kego/pii/__init__.py
kego/pii/tokenize.py
kego/plotting/__init__.py
kego/plotting/analysis.py
kego/plotting/axes.py
kego/plotting/colormesh.py
kego/plotting/figures.py
kego/plotting/grid_plot.py
kego/plotting/histogram_2d_utils.py
kego/plotting/histograms.py
kego/plotting/lines.py
kego/plotting/timeseries.py
kego/plotting/utils_plotting.py
kego/plotting/value_counts.py
kego/torch/__init__.py
kego/torch/devices.py
kego-0.5.0.dist-info/METADATA
kego-0.5.0.dist-info/WHEEL
kego-0.5.0.dist-info/RECORD
