Metadata-Version: 2.4
Name: kego
Version: 0.5.0
Summary: Helpers for quick ML analysis of kaggle competitions.
Requires-Python: >=3.10
Requires-Dist: autogluon>=1.2
Requires-Dist: ipykernel>=5.5.6
Requires-Dist: kaggle>=1.6.6
Requires-Dist: lifelines>=0.30.0
Requires-Dist: matplotlib>=3.7.0
Requires-Dist: numpy>=1.26.4
Requires-Dist: pandas>=2.2.0
Requires-Dist: python-dotenv>=1.0.1
Requires-Dist: scikit-learn>=1.5.0
Requires-Dist: tqdm>=4.66.4
